{
  "hub_url": "https://hub.spacestation14.com",
  "advertisement_interval_minutes": 2,
  "request_timeout_seconds": 30,
  "max_retries": 3,
  "retry_delay_ms": 3000,
  "auto_test_proxies": true,
  "proxy_test_timeout_seconds": 10,
  "socks5_proxy_list_file": "socks5_proxy_list.txt",
  "proxy_username": "",
  "proxy_password": "",
  "servers": [
    {
      "address": "ss14://localhost:1212",
      "display_name": "t.me/VT_SS14 | PJB go smd, hub will cry soon"
    },
    {
      "address": "ss14://localhost:1213",
      "display_name": "t.me/VT_SS14 | PJB go smd, hub will cry soon"
    },
    {
      "address": "ss14://localhost:1214",
      "display_name": "t.me/VT_SS14 | PJB go smd, hub will cry soon"
    },
    {
      "address": "ss14://localhost:1215",
      "display_name": "t.me/VT_SS14 | PJB go smd, hub will cry soon"
    },
    {
      "address": "ss14://localhost:1216",
      "display_name": "t.me/VT_SS14 | PJB go smd, hub will cry soon"
    },
    {
      "address": "ss14://localhost:1217",
      "display_name": "t.me/VT_SS14 | PJB go smd, hub will cry soon"
    },
    {
      "address": "ss14://localhost:1218",
      "display_name": "t.me/VT_SS14 | PJB go smd, hub will cry soon"
    },
    {
      "address": "ss14://localhost:1219",
      "display_name": "t.me/VT_SS14 | PJB go smd, hub will cry soon"
    },
    {
      "address": "ss14://localhost:1220",
      "display_name": "t.me/VT_SS14 | PJB go smd, hub will cry soon"
    },
    {
      "address": "ss14://localhost:1221",
      "display_name": "t.me/VT_SS14 | PJB go smd, hub will cry soon"
    },
    {
      "address": "ss14://localhost:1222",
      "display_name": "t.me/VT_SS14 | PJB go smd, hub will cry soon"
    },
    {
      "address": "ss14://localhost:1223",
      "display_name": "t.me/VT_SS14 | PJB go smd, hub will cry soon"
    },
    {
      "address": "ss14://localhost:1224",
      "display_name": "t.me/VT_SS14 | PJB go smd, hub will cry soon"
    }
  ]
}
